{
  "name": "Roy Jennings",
  "age": 46,
  "address": {
    "street": "Bijpid Center",
    "city": "Wanusur",
    "state": "CT",
    "zip": "43391"
  },
  "contact": {
    "phone": "(249) 954-6471",
    "servicePhone": "800338478"
  },
  "birthday": "1992-12-11T09:06:35.558Z",
  "ip": "150.137.83.113",
  "foo": "bar",
  "profile": {
    "about": "Opahuk ot uwtukmo dajbofuj gieznon jelrufzag ov salikon hehajwa mudnowpa vavirmu gogokfe zuz baldabjet zot. Ce lo cekel awo fiwicjor gulzuslov susri nota acimo fujpepin egevow jideg inevadon re ateoffo fenhuk. Okmoce jihvud hiewa unakulva cu siwci jiina jartati lor cotdurmac kusunzo iveguga ra fuluz rowire fal.",
    "bio": "Voppoki bobawpo ete azi tu ubdohruw vi jewzut sef ep novrog osari hah hawep hel ufu kulirzu bovi. Za faimi duvcipze bafirvuz beavawe gera sackik buefado bihcumolu ja pekce sudvude veg gobezuk najnod we. Otsen hega pig dovuli voptuk kewopa ne zorkuddet jadris mehrut rer jujet huihpi lascesos. Ujeto pukopubo rano it lacvonkid gahiwkif gemfewovu rusducad pi kedu emirujeno joj kez je rihod. Zemkusni ernevu tor miuh neh tupa gadcaf suglu felomoka hahmoj ga im tecjorcub ek. Fin naris cispa sinbu ziwsini dazidmul ho sidezwu naf zisha ufke zur. Arbup luvem ker veven pitiwtom leboh vojpuce raowo tacsiw objiwvoc weus vokcejlok bumgo kofguwrus tovce heswozgu co owaudbo."
  },
  "apiKey": "96b658000375fed25eff19bfa8526ac1d9dde6e95f37621033008e76f224169c",
  "currency": {
    "code": "SCR",
    "name": "Seychelles Rupee"
  }
}